python_json_config/__init__.py
python_json_config/__version__.py
python_json_config/config_builder.py
python_json_config/config_node.py
python_json_config/utils.py
python_json_config/transformers/__init__.py
python_json_config/transformers/generic_transformers.py
python_json_config/validators/__init__.py
python_json_config/validators/generic_validators.py
python_json_config/validators/network_validators.py
tests/config_node/__init__.py
tests/config_node/conftest.py
tests/config_node/test_crud.py
tests/config_node/test_iterators.py
tests/config_node/test_serialization.py
tests/config_node/test_utils.py
tests/transformers/__init__.py
tests/transformers/generic_transformers_test.py
tests/utils/__init__.py
tests/utils/test_utils.py
tests/validators/__init__.py
tests/validators/generic_validators_test.py
tests/validators/network_validators_test.py
python_json_config-1.2.3.dist-info/LICENSE
python_json_config-1.2.3.dist-info/METADATA
python_json_config-1.2.3.dist-info/WHEEL
python_json_config-1.2.3.dist-info/top_level.txt
python_json_config-1.2.3.dist-info/RECORD
