Metadata-Version: 2.1
Name: python-json-config
Version: 1.2.3
Summary: This library allows to load json configs and access the values like members (i.e., via dots), validate config field types and values and transform config fields.
Home-page: https://github.com/janehmueller/python-config
Author: Jan Ehmueller
Author-email: jan@ehmueller.de
License: MIT
Platform: UNKNOWN
Classifier: License :: OSI Approved :: MIT License
Classifier: Programming Language :: Python
Classifier: Programming Language :: Python :: 3
Classifier: Programming Language :: Python :: 3 :: Only
Classifier: Programming Language :: Python :: 3.6
Classifier: Programming Language :: Python :: 3.7
Classifier: Programming Language :: Python :: Implementation :: PyPy
Classifier: Intended Audience :: Developers
Requires-Python: >=3.6
Requires-Dist: jsonschema
Requires-Dist: msgpack
